mlflow_plugin_manager/__init__.py
mlflow_plugin_manager/api/__init__.py
mlflow_plugin_manager/api/endpoints.py
mlflow_plugin_manager/static/App.js
mlflow_plugin_manager/static/menu_injector_v2.js
mlflow_plugin_manager/static/menu_injector_v3.js
mlflow_plugin_manager/static/mlflow-style.css
mlflow_plugin_manager/static/script.js
mlflow_plugin_manager/static/style.css
mlflow_plugin_manager/templates/plugin_manager.html
mlflow_plugin_manager-0.2.0.dist-info/licenses/LICENSE
mlflow_plugin_manager-0.2.0.dist-info/METADATA
mlflow_plugin_manager-0.2.0.dist-info/WHEEL
mlflow_plugin_manager-0.2.0.dist-info/entry_points.txt
mlflow_plugin_manager-0.2.0.dist-info/top_level.txt
mlflow_plugin_manager-0.2.0.dist-info/RECORD
