Metadata-Version: 2.4
Name: mlflow-plugin-manager
Version: 0.2.0
Summary: PyPI package management integrated directly into MLflow's web interface
Home-page: https://github.com/thijsdezoete/mlflow-plugin-manager
Author: Thijs de Zoete
Author-email: 
Project-URL: Bug Tracker, https://github.com/thijsdezoete/mlflow-plugin-manager/issues
Project-URL: Documentation, https://thijsdezoete.github.io/mlflow-plugin-manager/
Project-URL: Source, https://github.com/thijsdezoete/mlflow-plugin-manager
Classifier: Development Status :: 4 - Beta
Classifier: Intended Audience :: Developers
Classifier: Intended Audience :: Science/Research
Classifier: Topic :: Scientific/Engineering :: Artificial Intelligence
Classifier: Topic :: Software Development :: Libraries :: Python Modules
Classifier: License :: OSI Approved :: MIT License
Classifier: Operating System :: OS Independent
Classifier: Programming Language :: Python :: 3
Classifier: Programming Language :: Python :: 3.10
Classifier: Programming Language :: Python :: 3.11
Classifier: Programming Language :: Python :: 3.12
Classifier: Programming Language :: Python :: 3.13
Requires-Python: >=3.10
License-File: LICENSE
Requires-Dist: flask>=2.0.0
Requires-Dist: requests>=2.25.0
Requires-Dist: packaging>=20.0
Requires-Dist: asgiref>=3.4.0
Requires-Dist: starlette>=0.27.0
Provides-Extra: dev
Requires-Dist: pytest>=7.0.0; extra == "dev"
Requires-Dist: black>=22.0.0; extra == "dev"
Requires-Dist: flake8>=4.0.0; extra == "dev"
Provides-Extra: server
Requires-Dist: flask-sqlalchemy>=2.5.0; extra == "server"
Requires-Dist: flask-migrate>=3.0.0; extra == "server"
Requires-Dist: flask-login>=0.5.0; extra == "server"
Dynamic: author
Dynamic: classifier
Dynamic: description
Dynamic: description-content-type
Dynamic: home-page
Dynamic: license-file
Dynamic: project-url
Dynamic: provides-extra
Dynamic: requires-dist
Dynamic: requires-python
Dynamic: summary
